opalalgorithms/__init__.py
opalalgorithms/core/__init__.py
opalalgorithms/core/base.py
opalalgorithms/utils/__init__.py
opalalgorithms/utils/algorithmrunner.py
opalalgorithms/utils/bandicoot_format.py
opalalgorithms/utils/datagenerator.py
opalalgorithms/utils/date_helper.py
opalalgorithms-0.1.4.dist-info/METADATA
opalalgorithms-0.1.4.dist-info/RECORD
opalalgorithms-0.1.4.dist-info/WHEEL
opalalgorithms-0.1.4.dist-info/dependency_links.txt
opalalgorithms-0.1.4.dist-info/top_level.txt
