Metadata-Version: 2.1
Name: opalalgorithms
Version: 0.1.4
Summary: OPAL Algorithms. Package to implement algorithms to be run on OPAL platform.
Home-page: https://github.com/shubhamjain0594/opalalgorithms
Author: Shubham Jain, Axel Oehmichen, Yves-Alexandre De Montjoye
Author-email: shubhamjain0594@gmail.com
License: MIT
Keywords: python2,python3,opal,opalalgorithms
Platform: UNKNOWN
Classifier: Development Status :: 5 - Production/Stable
Classifier: Environment :: Web Environment
Classifier: Intended Audience :: Developers
Classifier: License :: OSI Approved :: MIT License
Classifier: Operating System :: OS Independent
Classifier: Programming Language :: Python
Requires-Dist: setuptools
Requires-Dist: bandicoot
Requires-Dist: six
Requires-Dist: configargparse
Requires-Dist: codejail
